src/lancerkit/__init__.py
src/lancerkit/lancerkit.py
Lancerkit-1.0.0.dist-info/METADATA
Lancerkit-1.0.0.dist-info/WHEEL
Lancerkit-1.0.0.dist-info/top_level.txt
Lancerkit-1.0.0.dist-info/RECORD
