Metadata-Version: 2.1
Name: Lancerkit
Version: 1.0.0
Summary: Python SDK for Lancerkit API
Home-page: https://lancerkit.com
Author: Alexis Clarembeau
Author-email: contact@lancerkit.com
